{
  "version": "5.2.1",
  "flags": {},
  "shapes": [
    {
      "label": "wrist",
      "points": [
        [
          85.48703002929688,
          188.38492584228516
        ]
      ],
      "group_id": null,
      "shape_type": "point",
      "flags": {}
    },
    {
      "label": "thumb1",
      "points": [
        [
          123.3028087615967,
          179.26060485839844
        ]
      ],
      "group_id": null,
      "shape_type": "point",
      "flags": {}
    },
    {
      "label": "thumb2",
      "points": [
        [
          149.03377151489258,
          154.48990440368652
        ]
      ],
      "group_id": null,
      "shape_type": "point",
      "flags": {}
    },
    {
      "label": "thumb3",
      "points": [
        [
          159.53039360046387,
          128.9008674621582
        ]
      ],
      "group_id": null,
      "shape_type": "point",
      "flags": {}
    },
    {
      "label": "thumb4",
      "points": [
        [
          161.9429054260254,
          108.06037044525148
        ]
      ],
      "group_id": null,
      "shape_type": "point",
      "flags": {}
    },
    {
      "label": "index1",
      "points": [
        [
          128.56060600280762,
          112.25650787353517
        ]
      ],
      "group_id": null,
      "shape_type": "point",
      "flags": {}
    },
    {
      "label": "index2",
      "points": [
        [
          140.90556144714355,
          81.63190174102783
        ]
      ],
      "group_id": null,
      "shape_type": "point",
      "flags": {}
    },
    {
      "label": "index3",
      "points": [
        [
          149.90687561035156,
          66.08716011047363
        ]
      ],
      "group_id": null,
      "shape_type": "point",
      "flags": {}
    },
    {
      "label": "index4",
      "points": [
        [
          158.05165481567383,
          55.36255550384522
        ]
      ],
      "group_id": null,
      "shape_type": "point",
      "flags": {}
    },
    {
      "label": "middle1",
      "points": [
        [
          107.81149291992189,
          103.54624843597414
        ]
      ],
      "group_id": null,
      "shape_type": "point",
      "flags": {}
    },
    {
      "label": "middle2",
      "points": [
        [
          115.83191680908205,
          67.14357280731201
        ]
      ],
      "group_id": null,
      "shape_type": "point",
      "flags": {}
    },
    {
      "label": "middle3",
      "points": [
        [
          123.52952957153322,
          45.99013137817383
        ]
      ],
      "group_id": null,
      "shape_type": "point",
      "flags": {}
    },
    {
      "label": "middle4",
      "points": [
        [
          131.16420364379883,
          30.97489452362061
        ]
      ],
      "group_id": null,
      "shape_type": "point",
      "flags": {}
    },
    {
      "label": "ring1",
      "points": [
        [
          87.80795097351074,
          102.13889980316164
        ]
      ],
      "group_id": null,
      "shape_type": "point",
      "flags": {}
    },
    {
      "label": "ring2",
      "points": [
        [
          93.95755767822266,
          67.26743412017822
        ]
      ],
      "group_id": null,
      "shape_type": "point",
      "flags": {}
    },
    {
      "label": "ring3",
      "points": [
        [
          102.05114746093751,
          48.058109283447266
        ]
      ],
      "group_id": null,
      "shape_type": "point",
      "flags": {}
    },
    {
      "label": "ring4",
      "points": [
        [
          111.43152236938478,
          34.03989124298096
        ]
      ],
      "group_id": null,
      "shape_type": "point",
      "flags": {}
    },
    {
      "label": "pinky1",
      "points": [
        [
          68.19027900695801,
          107.22210693359376
        ]
      ],
      "group_id": null,
      "shape_type": "point",
      "flags": {}
    },
    {
      "label": "pinky2",
      "points": [
        [
          65.1748161315918,
          81.00607299804688
        ]
      ],
      "group_id": null,
      "shape_type": "point",
      "flags": {}
    },
    {
      "label": "pinky3",
      "points": [
        [
          68.15098571777344,
          66.63366794586182
        ]
      ],
      "group_id": null,
      "shape_type": "point",
      "flags": {}
    },
    {
      "label": "pinky4",
      "points": [
        [
          74.77385425567627,
          55.93940448760987
        ]
      ],
      "group_id": null,
      "shape_type": "point",
      "flags": {}
    }
  ],
  "imagePath": "../hand_images/hand_0490.jpg",
  "imageData": null,
  "imageHeight": 224,
  "imageWidth": 224,
  "coord_type": "pixel"
}