{
  "version": "5.2.1",
  "flags": {},
  "shapes": [
    {
      "label": "wrist",
      "points": [
        [
          270.8618903160095,
          1083.884048461914
        ]
      ],
      "group_id": null,
      "shape_type": "point",
      "flags": {}
    },
    {
      "label": "thumb1",
      "points": [
        [
          273.9819002151489,
          923.3546447753906
        ]
      ],
      "group_id": null,
      "shape_type": "point",
      "flags": {}
    },
    {
      "label": "thumb2",
      "points": [
        [
          229.62584495544434,
          768.5198974609375
        ]
      ],
      "group_id": null,
      "shape_type": "point",
      "flags": {}
    },
    {
      "label": "thumb3",
      "points": [
        [
          232.3769760131836,
          650.6193542480469
        ]
      ],
      "group_id": null,
      "shape_type": "point",
      "flags": {}
    },
    {
      "label": "thumb4",
      "points": [
        [
          282.22113132476807,
          528.0319976806641
        ]
      ],
      "group_id": null,
      "shape_type": "point",
      "flags": {}
    },
    {
      "label": "index1",
      "points": [
        [
          259.51942920684814,
          632.1371459960938
        ]
      ],
      "group_id": null,
      "shape_type": "point",
      "flags": {}
    },
    {
      "label": "index2",
      "points": [
        [
          306.5005946159363,
          430.88401794433594
        ]
      ],
      "group_id": null,
      "shape_type": "point",
      "flags": {}
    },
    {
      "label": "index3",
      "points": [
        [
          340.83565950393677,
          295.3150749206543
        ]
      ],
      "group_id": null,
      "shape_type": "point",
      "flags": {}
    },
    {
      "label": "index4",
      "points": [
        [
          382.9378652572632,
          177.20962524414062
        ]
      ],
      "group_id": null,
      "shape_type": "point",
      "flags": {}
    },
    {
      "label": "middle1",
      "points": [
        [
          278.4482717514038,
          665.5342864990234
        ]
      ],
      "group_id": null,
      "shape_type": "point",
      "flags": {}
    },
    {
      "label": "middle2",
      "points": [
        [
          333.8600707054138,
          440.97442626953125
        ]
      ],
      "group_id": null,
      "shape_type": "point",
      "flags": {}
    },
    {
      "label": "middle3",
      "points": [
        [
          385.4981517791748,
          285.20090103149414
        ]
      ],
      "group_id": null,
      "shape_type": "point",
      "flags": {}
    },
    {
      "label": "middle4",
      "points": [
        [
          436.5811014175415,
          154.1964340209961
        ]
      ],
      "group_id": null,
      "shape_type": "point",
      "flags": {}
    },
    {
      "label": "ring1",
      "points": [
        [
          294.43333625793457,
          721.4263916015625
        ]
      ],
      "group_id": null,
      "shape_type": "point",
      "flags": {}
    },
    {
      "label": "ring2",
      "points": [
        [
          337.0308494567871,
          515.2020263671875
        ]
      ],
      "group_id": null,
      "shape_type": "point",
      "flags": {}
    },
    {
      "label": "ring3",
      "points": [
        [
          375.3640365600586,
          366.2144088745117
        ]
      ],
      "group_id": null,
      "shape_type": "point",
      "flags": {}
    },
    {
      "label": "ring4",
      "points": [
        [
          417.11058139801025,
          248.9723777770996
        ]
      ],
      "group_id": null,
      "shape_type": "point",
      "flags": {}
    },
    {
      "label": "pinky1",
      "points": [
        [
          312.30671882629395,
          787.2335815429688
        ]
      ],
      "group_id": null,
      "shape_type": "point",
      "flags": {}
    },
    {
      "label": "pinky2",
      "points": [
        [
          344.6454906463623,
          638.0889129638672
        ]
      ],
      "group_id": null,
      "shape_type": "point",
      "flags": {}
    },
    {
      "label": "pinky3",
      "points": [
        [
          384.41333770751953,
          524.0652465820312
        ]
      ],
      "group_id": null,
      "shape_type": "point",
      "flags": {}
    },
    {
      "label": "pinky4",
      "points": [
        [
          419.6984624862671,
          432.9241180419922
        ]
      ],
      "group_id": null,
      "shape_type": "point",
      "flags": {}
    }
  ],
  "imagePath": "../hand_images/hand_0087.jpg",
  "imageData": null,
  "imageHeight": 1280,
  "imageWidth": 720,
  "coord_type": "pixel"
}