{
  "version": "5.2.1",
  "flags": {},
  "shapes": [
    {
      "label": "wrist",
      "points": [
        [
          73.1413402557373,
          152.25213623046875
        ]
      ],
      "group_id": null,
      "shape_type": "point",
      "flags": {}
    },
    {
      "label": "thumb1",
      "points": [
        [
          89.99930953979492,
          131.17595291137695
        ]
      ],
      "group_id": null,
      "shape_type": "point",
      "flags": {}
    },
    {
      "label": "thumb2",
      "points": [
        [
          94.5578384399414,
          111.7125234603882
        ]
      ],
      "group_id": null,
      "shape_type": "point",
      "flags": {}
    },
    {
      "label": "thumb3",
      "points": [
        [
          98.65258502960205,
          97.780348777771
        ]
      ],
      "group_id": null,
      "shape_type": "point",
      "flags": {}
    },
    {
      "label": "thumb4",
      "points": [
        [
          100.2905731201172,
          85.68118000030518
        ]
      ],
      "group_id": null,
      "shape_type": "point",
      "flags": {}
    },
    {
      "label": "index1",
      "points": [
        [
          61.02187728881837,
          89.39916896820068
        ]
      ],
      "group_id": null,
      "shape_type": "point",
      "flags": {}
    },
    {
      "label": "index2",
      "points": [
        [
          92.93426990509033,
          83.22382068634033
        ]
      ],
      "group_id": null,
      "shape_type": "point",
      "flags": {}
    },
    {
      "label": "index3",
      "points": [
        [
          100.82750129699708,
          95.2325668334961
        ]
      ],
      "group_id": null,
      "shape_type": "point",
      "flags": {}
    },
    {
      "label": "index4",
      "points": [
        [
          98.34960079193115,
          104.6348114013672
        ]
      ],
      "group_id": null,
      "shape_type": "point",
      "flags": {}
    },
    {
      "label": "middle1",
      "points": [
        [
          60.268669128417976,
          88.4231185913086
        ]
      ],
      "group_id": null,
      "shape_type": "point",
      "flags": {}
    },
    {
      "label": "middle2",
      "points": [
        [
          96.82572746276855,
          83.94996547698975
        ]
      ],
      "group_id": null,
      "shape_type": "point",
      "flags": {}
    },
    {
      "label": "middle3",
      "points": [
        [
          101.91619110107423,
          98.40604400634766
        ]
      ],
      "group_id": null,
      "shape_type": "point",
      "flags": {}
    },
    {
      "label": "middle4",
      "points": [
        [
          96.98394203186035,
          106.58020305633546
        ]
      ],
      "group_id": null,
      "shape_type": "point",
      "flags": {}
    },
    {
      "label": "ring1",
      "points": [
        [
          64.45059394836426,
          91.06716442108154
        ]
      ],
      "group_id": null,
      "shape_type": "point",
      "flags": {}
    },
    {
      "label": "ring2",
      "points": [
        [
          99.70000553131104,
          91.77406311035156
        ]
      ],
      "group_id": null,
      "shape_type": "point",
      "flags": {}
    },
    {
      "label": "ring3",
      "points": [
        [
          101.10549163818361,
          105.45846843719484
        ]
      ],
      "group_id": null,
      "shape_type": "point",
      "flags": {}
    },
    {
      "label": "ring4",
      "points": [
        [
          94.28719806671143,
          112.12424850463869
        ]
      ],
      "group_id": null,
      "shape_type": "point",
      "flags": {}
    },
    {
      "label": "pinky1",
      "points": [
        [
          72.20848178863525,
          96.36811351776123
        ]
      ],
      "group_id": null,
      "shape_type": "point",
      "flags": {}
    },
    {
      "label": "pinky2",
      "points": [
        [
          99.6737699508667,
          102.14817905426027
        ]
      ],
      "group_id": null,
      "shape_type": "point",
      "flags": {}
    },
    {
      "label": "pinky3",
      "points": [
        [
          100.66048145294191,
          112.23897743225099
        ]
      ],
      "group_id": null,
      "shape_type": "point",
      "flags": {}
    },
    {
      "label": "pinky4",
      "points": [
        [
          95.06718921661377,
          116.72839927673341
        ]
      ],
      "group_id": null,
      "shape_type": "point",
      "flags": {}
    }
  ],
  "imagePath": "../hand_images/hand_1342.jpg",
  "imageData": null,
  "imageHeight": 224,
  "imageWidth": 224,
  "coord_type": "pixel"
}