{
  "version": "5.2.1",
  "flags": {},
  "shapes": [
    {
      "label": "wrist",
      "points": [
        [
          64.5271577835083,
          211.63245391845706
        ]
      ],
      "group_id": null,
      "shape_type": "point",
      "flags": {}
    },
    {
      "label": "thumb1",
      "points": [
        [
          106.21592235565187,
          203.54728889465335
        ]
      ],
      "group_id": null,
      "shape_type": "point",
      "flags": {}
    },
    {
      "label": "thumb2",
      "points": [
        [
          135.06010055541992,
          176.54705810546875
        ]
      ],
      "group_id": null,
      "shape_type": "point",
      "flags": {}
    },
    {
      "label": "thumb3",
      "points": [
        [
          149.9257411956787,
          148.54309272766113
        ]
      ],
      "group_id": null,
      "shape_type": "point",
      "flags": {}
    },
    {
      "label": "thumb4",
      "points": [
        [
          158.95063400268555,
          128.03871154785156
        ]
      ],
      "group_id": null,
      "shape_type": "point",
      "flags": {}
    },
    {
      "label": "index1",
      "points": [
        [
          125.31197357177736,
          136.20211601257324
        ]
      ],
      "group_id": null,
      "shape_type": "point",
      "flags": {}
    },
    {
      "label": "index2",
      "points": [
        [
          135.20591163635254,
          101.50368499755861
        ]
      ],
      "group_id": null,
      "shape_type": "point",
      "flags": {}
    },
    {
      "label": "index3",
      "points": [
        [
          140.0192928314209,
          83.94979190826416
        ]
      ],
      "group_id": null,
      "shape_type": "point",
      "flags": {}
    },
    {
      "label": "index4",
      "points": [
        [
          144.9877643585205,
          70.14659881591797
        ]
      ],
      "group_id": null,
      "shape_type": "point",
      "flags": {}
    },
    {
      "label": "middle1",
      "points": [
        [
          107.00632095336915,
          127.95366287231447
        ]
      ],
      "group_id": null,
      "shape_type": "point",
      "flags": {}
    },
    {
      "label": "middle2",
      "points": [
        [
          113.75392532348634,
          89.38543033599854
        ]
      ],
      "group_id": null,
      "shape_type": "point",
      "flags": {}
    },
    {
      "label": "middle3",
      "points": [
        [
          119.44465637207033,
          68.51040649414062
        ]
      ],
      "group_id": null,
      "shape_type": "point",
      "flags": {}
    },
    {
      "label": "middle4",
      "points": [
        [
          123.73299217224123,
          53.03912448883057
        ]
      ],
      "group_id": null,
      "shape_type": "point",
      "flags": {}
    },
    {
      "label": "ring1",
      "points": [
        [
          89.74650001525879,
          127.05694007873537
        ]
      ],
      "group_id": null,
      "shape_type": "point",
      "flags": {}
    },
    {
      "label": "ring2",
      "points": [
        [
          97.62192058563232,
          89.14900302886963
        ]
      ],
      "group_id": null,
      "shape_type": "point",
      "flags": {}
    },
    {
      "label": "ring3",
      "points": [
        [
          103.25479984283449,
          69.21826648712158
        ]
      ],
      "group_id": null,
      "shape_type": "point",
      "flags": {}
    },
    {
      "label": "ring4",
      "points": [
        [
          108.99441719055177,
          53.73992824554444
        ]
      ],
      "group_id": null,
      "shape_type": "point",
      "flags": {}
    },
    {
      "label": "pinky1",
      "points": [
        [
          72.45806694030762,
          132.9411735534668
        ]
      ],
      "group_id": null,
      "shape_type": "point",
      "flags": {}
    },
    {
      "label": "pinky2",
      "points": [
        [
          75.05771923065186,
          106.29741287231447
        ]
      ],
      "group_id": null,
      "shape_type": "point",
      "flags": {}
    },
    {
      "label": "pinky3",
      "points": [
        [
          76.88404941558838,
          91.71078395843506
        ]
      ],
      "group_id": null,
      "shape_type": "point",
      "flags": {}
    },
    {
      "label": "pinky4",
      "points": [
        [
          80.7248649597168,
          80.05763339996338
        ]
      ],
      "group_id": null,
      "shape_type": "point",
      "flags": {}
    }
  ],
  "imagePath": "../hand_images/hand_0728.jpg",
  "imageData": null,
  "imageHeight": 224,
  "imageWidth": 224,
  "coord_type": "pixel"
}