{
  "version": "5.2.1",
  "flags": {},
  "shapes": [
    {
      "label": "wrist",
      "points": [
        [
          1087.2861328125,
          2558.673095703125
        ]
      ],
      "group_id": null,
      "shape_type": "point",
      "flags": {}
    },
    {
      "label": "thumb1",
      "points": [
        [
          1796.148193359375,
          2579.8701171875
        ]
      ],
      "group_id": null,
      "shape_type": "point",
      "flags": {}
    },
    {
      "label": "thumb2",
      "points": [
        [
          2295.6011352539062,
          2402.3916015625
        ]
      ],
      "group_id": null,
      "shape_type": "point",
      "flags": {}
    },
    {
      "label": "thumb3",
      "points": [
        [
          2672.1807861328125,
          2020.81787109375
        ]
      ],
      "group_id": null,
      "shape_type": "point",
      "flags": {}
    },
    {
      "label": "thumb4",
      "points": [
        [
          2688.7022094726562,
          1632.5440673828125
        ]
      ],
      "group_id": null,
      "shape_type": "point",
      "flags": {}
    },
    {
      "label": "index1",
      "points": [
        [
          2078.3331298828125,
          1606.6417236328125
        ]
      ],
      "group_id": null,
      "shape_type": "point",
      "flags": {}
    },
    {
      "label": "index2",
      "points": [
        [
          2448.5343017578125,
          1003.708740234375
        ]
      ],
      "group_id": null,
      "shape_type": "point",
      "flags": {}
    },
    {
      "label": "index3",
      "points": [
        [
          2567.578857421875,
          749.45751953125
        ]
      ],
      "group_id": null,
      "shape_type": "point",
      "flags": {}
    },
    {
      "label": "index4",
      "points": [
        [
          2560.0413208007812,
          715.4551391601562
        ]
      ],
      "group_id": null,
      "shape_type": "point",
      "flags": {}
    },
    {
      "label": "middle1",
      "points": [
        [
          1683.8052978515625,
          1411.85986328125
        ]
      ],
      "group_id": null,
      "shape_type": "point",
      "flags": {}
    },
    {
      "label": "middle2",
      "points": [
        [
          1928.397216796875,
          617.6795043945312
        ]
      ],
      "group_id": null,
      "shape_type": "point",
      "flags": {}
    },
    {
      "label": "middle3",
      "points": [
        [
          2060.3472290039062,
          385.3524169921875
        ]
      ],
      "group_id": null,
      "shape_type": "point",
      "flags": {}
    },
    {
      "label": "middle4",
      "points": [
        [
          2129.7022705078125,
          358.223876953125
        ]
      ],
      "group_id": null,
      "shape_type": "point",
      "flags": {}
    },
    {
      "label": "ring1",
      "points": [
        [
          1293.970458984375,
          1337.7987060546875
        ]
      ],
      "group_id": null,
      "shape_type": "point",
      "flags": {}
    },
    {
      "label": "ring2",
      "points": [
        [
          1389.5428161621094,
          601.18701171875
        ]
      ],
      "group_id": null,
      "shape_type": "point",
      "flags": {}
    },
    {
      "label": "ring3",
      "points": [
        [
          1554.703125,
          409.26995849609375
        ]
      ],
      "group_id": null,
      "shape_type": "point",
      "flags": {}
    },
    {
      "label": "ring4",
      "points": [
        [
          1683.8475952148438,
          426.97003173828125
        ]
      ],
      "group_id": null,
      "shape_type": "point",
      "flags": {}
    },
    {
      "label": "pinky1",
      "points": [
        [
          955.0260314941406,
          1398.4498291015625
        ]
      ],
      "group_id": null,
      "shape_type": "point",
      "flags": {}
    },
    {
      "label": "pinky2",
      "points": [
        [
          1030.2376098632812,
          840.7935180664062
        ]
      ],
      "group_id": null,
      "shape_type": "point",
      "flags": {}
    },
    {
      "label": "pinky3",
      "points": [
        [
          1163.7102355957031,
          732.4677734375
        ]
      ],
      "group_id": null,
      "shape_type": "point",
      "flags": {}
    },
    {
      "label": "pinky4",
      "points": [
        [
          1299.7261962890625,
          793.3885498046875
        ]
      ],
      "group_id": null,
      "shape_type": "point",
      "flags": {}
    }
  ],
  "imagePath": "../hand_images/hand_1103.jpg",
  "imageData": null,
  "imageHeight": 4096,
  "imageWidth": 3072,
  "coord_type": "pixel"
}